flask_opensearch/__init__.py
flask_opensearch/flask_opensearch.py
Flask_Opensearch-1.0.2.dist-info/LICENSE
Flask_Opensearch-1.0.2.dist-info/METADATA
Flask_Opensearch-1.0.2.dist-info/WHEEL
Flask_Opensearch-1.0.2.dist-info/top_level.txt
Flask_Opensearch-1.0.2.dist-info/RECORD
