Metadata-Version: 2.1
Name: Flask-Opensearch
Version: 1.0.2
Summary: Flask extension for opensearch integration
Home-page: https://github.com/galbwe/Flask-Opensearch
Author: Wes Galbraith
Author-email: galbwe92@gmail.com
License: MIT
Platform: any
Classifier: Environment :: Web Environment
Classifier: Intended Audience :: Developers
Classifier: License :: OSI Approved :: MIT License
Classifier: Operating System :: OS Independent
Classifier: Programming Language :: Python
Classifier: Topic :: Internet :: WWW/HTTP :: Dynamic Content
Classifier: Topic :: Software Development :: Libraries :: Python Modules
Requires-Python: >=3.6
License-File: LICENSE
Requires-Dist: Flask
Requires-Dist: opensearch-py
Requires-Dist: aws-requests-auth
